pymath_compute-0.3.2.dist-info/METADATA
pymath_compute-0.3.2.dist-info/WHEEL
pymath_compute/methods/__init__.py
pymath_compute/methods/regularity.py
pymath_compute/methods/search.py
pymath_compute/methods/opt_methods.py
pymath_compute/methods/training.py
pymath_compute/methods/interpolation.py
pymath_compute/engine/__init__.pyi
pymath_compute/engine/optimization_methods.pyi
pymath_compute/__init__.py
pymath_compute/solvers/__init__.py
pymath_compute/solvers/opt_solver.py
pymath_compute/model/variable.py
pymath_compute/model/__init__.py
pymath_compute/model/expression.py
pymath_compute/model/types.py
pymath_compute/model/function.py
pymath_compute/py.typed
pymath_compute/utils/graph.py
pymath_compute/utils/math_utils.py
pymath_compute/examples/README.md
pymath_compute/examples/opt_methods/revolution_solid_minimum.py
pymath_compute/engine.cpython-311-arm-linux-gnueabihf.so
pymath_compute-0.3.2.dist-info/RECORD
