Metadata-Version: 2.3
Name: pymath_compute
Version: 0.3.2
Summary: Tool to handle mathematical operations using Variables and Mathematical Expressions.
Keywords: scientific_computing,applied_math,optimization
Home-Page: https://pymath.ricardoleal20.dev
Author: ricardoleal20 <rick.leal420@gmail.com>
Author-email: ricardoleal20 <rick.leal420@gmail.com>
License: MIT
Project-URL: Source Code, https://github.com/ricardoleal20/pymath_compute
